robokami/__init__.py
robokami/main.py
robokami/order.py
robokami_py-0.22.dist-info/METADATA
robokami_py-0.22.dist-info/WHEEL
robokami_py-0.22.dist-info/top_level.txt
robokami_py-0.22.dist-info/RECORD
