Metadata-Version: 2.1
Name: robokami-py
Version: 0.22
Summary: Robokami Client Python SDK
Home-page: https://github.com/Tideseed/robokami-py
Author: Robokami
License: Apache License 2.0
Classifier: Programming Language :: Python :: 3
Classifier: License :: OSI Approved :: Apache Software License
Classifier: Operating System :: OS Independent
Requires-Dist: sseclient-py (==1.7.2)
